zeroshot/__init__.py
zeroshot/classifier.py
zeroshot/classifier_test.py
zeroshot/downloader.py
zeroshot/downloader_test.py
zeroshot/feature_extractor.py
zeroshot/feature_extractor_test.py
zeroshot/logistic_regression.py
zeroshot/logistic_regression_test.py
zeroshot/preprocessing.py
zeroshot/preprocessing_test.py
zeroshot/test_files/test_model.json
zeroshot/utils.py
zeroshot/utils_test.py
zeroshot-0.1.11.dist-info/METADATA
zeroshot-0.1.11.dist-info/WHEEL
zeroshot-0.1.11.dist-info/RECORD
