Metadata-Version: 2.1
Name: zeroshot
Version: 0.1.11
Summary: Image classifier with zero-shot learning.
Home-page: https://github.com/moonshinelabs/zeroshot-python
License: MIT
Keywords: zeroshot,classifier,cv
Author: Nate Harada
Author-email: hello@usezeroshot.com
Requires-Python: >=3.10,<3.13
Classifier: License :: OSI Approved :: MIT License
Classifier: Programming Language :: Python :: 3
Classifier: Programming Language :: Python :: 3.10
Classifier: Programming Language :: Python :: 3.11
Provides-Extra: torch
Requires-Dist: mypy (>=1.6.0,<2.0.0)
Requires-Dist: numpy (>=1.26.0,<2.0.0)
Requires-Dist: onnxruntime (>=1.16.1,<2.0.0)
Requires-Dist: pillow (>=10.0.1,<11.0.0)
Requires-Dist: requests (>=2.31.0,<3.0.0)
Requires-Dist: torch (>=2.1.0,<3.0.0) ; extra == "torch"
Requires-Dist: types-pillow (>=10.0.0.3,<11.0.0.0)
Requires-Dist: xformers (>=0.0.22.post7,<0.0.23) ; extra == "torch"
Project-URL: Repository, https://github.com/moonshinelabs/zeroshot-python
